README.md
setup.py
carnivalmirror/__init__.py
carnivalmirror/calibration.py
carnivalmirror/sampling.py
carnivalmirror.egg-info/PKG-INFO
carnivalmirror.egg-info/SOURCES.txt
carnivalmirror.egg-info/dependency_links.txt
carnivalmirror.egg-info/not-zip-safe
carnivalmirror.egg-info/requires.txt
carnivalmirror.egg-info/top_level.txt