Metadata-Version: 1.0
Name: carnivalmirror
Version: 0.6.2
Summary: A tool to handle and simulate pinhole camera miscalibrations
Home-page: https://github.com/AleksandarPetrov/carnivalmirror
Author: Aleksandar Petrov
Author-email: alpetrov@ethz.ch
License: MIT
Platform: UNKNOWN
